mcp_context_graph/__init__.py
mcp_context_graph/__main__.py
mcp_context_graph/cli.py
mcp_context_graph/py.typed
mcp_context_graph/core/__init__.py
mcp_context_graph/core/edge.py
mcp_context_graph/core/graph.py
mcp_context_graph/core/node.py
mcp_context_graph/core/query.py
mcp_context_graph/ingest/__init__.py
mcp_context_graph/ingest/ingestor.py
mcp_context_graph/ingest/minifier.py
mcp_context_graph/ingest/normalizer.py
mcp_context_graph/ingest/tree_sitter_parser.py
mcp_context_graph/languages/__init__.py
mcp_context_graph/languages/base.py
mcp_context_graph/languages/registry.py
mcp_context_graph/languages/python/__init__.py
mcp_context_graph/languages/python/config.py
mcp_context_graph/languages/python/queries/calls.scm
mcp_context_graph/languages/python/queries/definitions.scm
mcp_context_graph/languages/python/queries/imports.scm
mcp_context_graph/languages/typescript/__init__.py
mcp_context_graph/languages/typescript/config.py
mcp_context_graph/languages/typescript/queries/calls.scm
mcp_context_graph/languages/typescript/queries/definitions.scm
mcp_context_graph/languages/typescript/queries/imports.scm
mcp_context_graph/mcp/__init__.py
mcp_context_graph/mcp/handlers.py
mcp_context_graph/mcp/resources.py
mcp_context_graph/mcp/server.py
mcp_context_graph/mcp/tools.py
mcp_context_graph/provenance/__init__.py
mcp_context_graph/provenance/interval_tree.py
mcp_context_graph/provenance/segment.py
mcp_context_graph/provenance/source_map.py
mcp_context_graph-0.1.0.dist-info/METADATA
mcp_context_graph-0.1.0.dist-info/WHEEL
mcp_context_graph-0.1.0.dist-info/entry_points.txt
mcp_context_graph-0.1.0.dist-info/licenses/LICENSE
mcp_context_graph-0.1.0.dist-info/RECORD
