Metadata-Version: 2.4
Name: mcp-context-graph
Version: 0.1.0
Summary: A zero-dependency, in-memory graph database providing a memory layer for local AI agents with AST-based dependency tracking and Token-Level Provenance via Source Maps.
Author: MCP Context Graph Team
License: MIT
License-File: LICENSE
Keywords: ai-agents,ast,context,graph,mcp,tree-sitter
Classifier: Development Status :: 3 - Alpha
Classifier: Intended Audience :: Developers
Classifier: License :: OSI Approved :: MIT License
Classifier: Programming Language :: Python :: 3
Classifier: Programming Language :: Python :: 3.12
Classifier: Programming Language :: Python :: 3.13
Classifier: Topic :: Software Development :: Libraries :: Python Modules
Requires-Python: >=3.12
Requires-Dist: mcp>=1.0.0
Requires-Dist: networkx>=3.4
Requires-Dist: pathspec>=0.12
Requires-Dist: pydantic>=2.5
Requires-Dist: tiktoken>=0.7
Requires-Dist: tree-sitter-javascript>=0.23
Requires-Dist: tree-sitter-python>=0.23
Requires-Dist: tree-sitter-typescript>=0.23
Requires-Dist: tree-sitter>=0.23
Provides-Extra: dev
Requires-Dist: black>=24.0; extra == 'dev'
Requires-Dist: hypothesis>=6.0; extra == 'dev'
Requires-Dist: mypy>=1.8; extra == 'dev'
Requires-Dist: pytest-cov>=4.0; extra == 'dev'
Requires-Dist: pytest>=8.0; extra == 'dev'
Requires-Dist: ruff>=0.2; extra == 'dev'
